fraise/__init__.py
fraise/application.py
fraise/phrases.py
fraise/words.py
fraise-1.5.2.dist-info/LICENSE
fraise-1.5.2.dist-info/METADATA
fraise-1.5.2.dist-info/WHEEL
fraise-1.5.2.dist-info/entry_points.txt
fraise-1.5.2.dist-info/top_level.txt
fraise-1.5.2.dist-info/RECORD
