Metadata-Version: 2.1
Name: fraise
Version: 1.5.2
Summary: Generate memorable pass phrases
Home-page: http://github.com/daveygit2050/fraise
Author: Dave Randall
Author-email: dave@goldsquare.co.uk
License: Apache v2
Platform: UNKNOWN
